tornext-0.0.1.data/scripts/tornext-admin
tornext-0.0.1.dist-info/entry_points.txt
tornext-0.0.1.dist-info/WHEEL
tornext-0.0.1.dist-info/top_level.txt
tornext-0.0.1.dist-info/DESCRIPTION.rst
tornext-0.0.1.dist-info/metadata.json
tornext-0.0.1.dist-info/RECORD
tornext-0.0.1.dist-info/METADATA
tornext/__init__.py
tornext/web.py
tornext/management.py
tornext/conf/__init__.py
tornext/conf/default_settings.py
