Metadata-Version: 2.0
Name: tornext
Version: 0.0.1
Summary: Tornext is a web framework based on tornado.
Home-page: UNKNOWN
Author: JZQT
Author-email: tjy.jzqt@qq.com
License: MIT
Keywords: web tornado tornext
Platform: UNKNOWN
Classifier: Programming Language :: Python :: 3
Classifier: Programming Language :: Python :: 3.3
Classifier: Programming Language :: Python :: 3.4
Classifier: Programming Language :: Python :: 3.5
Requires-Dist: tornado
